setup.py
clwapp/__init__.py
clwapp/clwapp.py
clwapp/factory.py
clwapp/utils.py
clwapp.egg-info/PKG-INFO
clwapp.egg-info/SOURCES.txt
clwapp.egg-info/dependency_links.txt
clwapp.egg-info/entry_points.txt
clwapp.egg-info/not-zip-safe
clwapp.egg-info/requires.txt
clwapp.egg-info/top_level.txt