Metadata-Version: 1.0
Name: clwapp
Version: 0.1.1
Summary: Command Line Web APP
Home-page: UNKNOWN
Author: Jeff Hammel
Author-email: jhammel@openplans.org
License: UNKNOWN
Platform: UNKNOWN
